preview_server/__init__.py
preview_server/__main__.py
preview_server/app.py
preview_server/cli.py
preview_server/config.py
preview_server/git.py
preview_server/persistence.py
preview_server/signing.py
preview_server/sub_server.py
preview_server/templates/__init__.py
preview_server/templates/status.html
preview_server/utils.py
preview_server-0.2a3.dist-info/WHEEL
preview_server-0.2a3.dist-info/entry_points.txt
preview_server-0.2a3.dist-info/METADATA
preview_server-0.2a3.dist-info/RECORD
