Metadata-Version: 2.4
Name: preview-server
Version: 0.2a3
Summary: Git-based preview deployment proxy server
Author: Simon Willison
License-Expression: Apache-2.0
Requires-Dist: httpx>=0.28.1,<1.0
Requires-Dist: pydantic>=2.12.5
Requires-Dist: starlette>=0.50.0
Requires-Dist: uvicorn>=0.38.0
Requires-Dist: websockets>=15.0
Requires-Python: >=3.11
Project-URL: CI, https://github.com/simonw/preview-server/actions
Project-URL: Changelog, https://github.com/simonw/preview-server/releases
Project-URL: Homepage, https://github.com/simonw/preview-server
Project-URL: Issues, https://github.com/simonw/preview-server/issues
